[
  {
    "title": "Regular Meeting Agenda",
    "url": "https://memphistn.gov/wp-content/uploads/2026/02/Virtual-Regular-Agenda-02-03-2026-Highlighted-Items.pdf",
    "documentType": "regular_agenda",
    "meetingDate": "2026-02-03T06:00:00.000Z",
    "rawLinkText": "Regular Meeting Agenda"
  },
  {
    "title": "Regular Meeting Documents",
    "url": "https://memphistn.gov/wp-content/uploads/2026/01/Regular-Agenda-Documents-02.03.2026.pdf",
    "documentType": "regular_docs",
    "meetingDate": "2026-02-03T06:00:00.000Z",
    "rawLinkText": "Regular Meeting Documents"
  },
  {
    "title": "Committee Meeting Agenda",
    "url": "https://memphistn.gov/wp-content/uploads/2026/02/Committee-Agenda-February-3-2026-v4-232026-12pm.pdf",
    "documentType": "committee_agenda",
    "meetingDate": "2026-02-03T06:00:00.000Z",
    "rawLinkText": "Committee Meeting Agenda"
  },
  {
    "title": "Committee Meeting Documents",
    "url": "https://memphistn.gov/wp-content/uploads/2026/01/Committe-Docs-232026-PUBLIC-Compressed.pdf",
    "documentType": "committee_docs",
    "meetingDate": "2026-02-03T06:00:00.000Z",
    "rawLinkText": "Committee Meeting Documents"
  },
  {
    "title": "Planning and Zoning Committee Documents",
    "url": "https://memphistn.gov/wp-content/uploads/2026/01/Planning-and-Zoning-Committee-Documents-2.3.2026.pdf",
    "documentType": "pz_committee_docs",
    "meetingDate": "2026-02-03T06:00:00.000Z",
    "rawLinkText": "Planning and Zoning Committee Documents"
  },
  {
    "title": "Cheryl Pesce Document",
    "url": "https://memphistn.gov/wp-content/uploads/2026/02/C.-Pesce-MLGW-Public.pdf",
    "documentType": "additional",
    "meetingDate": "2026-02-03T06:00:00.000Z",
    "rawLinkText": "Cheryl Pesce Document"
  },
  {
    "title": "Budget Resolution",
    "url": "https://memphistn.gov/wp-content/uploads/2026/02/RESOLUTION-TO-ALLOCATE-8000-IN-FY26-COUNCIL-COMMUNITY-GRANT-PROGRAM-FUNDS.pdf",
    "documentType": "budget",
    "meetingDate": "2026-02-03T06:00:00.000Z",
    "rawLinkText": "Budget Resolution"
  },
  {
    "title": "Winter Weather Update",
    "url": "https://memphistn.gov/wp-content/uploads/2026/02/Winter-Weather-update.pdf",
    "documentType": "additional",
    "meetingDate": "2026-02-03T06:00:00.000Z",
    "rawLinkText": "Winter Weather Update"
  },
  {
    "title": "Public Notice of Meeting and Viewing Instructions",
    "url": "https://memphistn.gov/wp-content/uploads/2026/02/Public-Notice-of-Meeting-and-Viewing-Instructions-February-32026.pdf",
    "documentType": "additional",
    "meetingDate": "2026-02-03T06:00:00.000Z",
    "rawLinkText": "Public Notice of Meeting and Viewing Instructions"
  }
]